maker/__init__.py
maker/_version.py
maker/_version.pyi
maker/appstore.py
maker/badge.py
maker/config.py
maker/const.py
maker/main.py
maker/py.typed
app_store_download_count_badge_maker-0.4.0.dist-info/METADATA
app_store_download_count_badge_maker-0.4.0.dist-info/WHEEL
app_store_download_count_badge_maker-0.4.0.dist-info/entry_points.txt
app_store_download_count_badge_maker-0.4.0.dist-info/licenses/LICENSE
app_store_download_count_badge_maker-0.4.0.dist-info/RECORD
