Metadata-Version: 2.4
Name: app-store-download-count-badge-maker
Version: 0.4.0
Summary: A command-line tool to create badges displaying the number of app downloads from App Store
Project-URL: repository, https://github.com/nnsnodnb/app-store-download-count-badge-maker
Author-email: nnsnodnb <nnsnodnb@gmail.com>
License-Expression: MIT
License-File: LICENSE
Keywords: app store,apple,badge,download count
Classifier: Development Status :: 5 - Production/Stable
Classifier: Environment :: Console
Classifier: Intended Audience :: Developers
Classifier: Intended Audience :: Information Technology
Classifier: License :: OSI Approved :: MIT License
Classifier: Operating System :: OS Independent
Classifier: Programming Language :: Python :: 3
Classifier: Programming Language :: Python :: 3.10
Classifier: Programming Language :: Python :: 3.11
Classifier: Programming Language :: Python :: 3.12
Classifier: Programming Language :: Python :: 3.13
Classifier: Topic :: Software Development :: Libraries :: Application Frameworks
Classifier: Topic :: Utilities
Requires-Python: <3.15,>=3.10
Requires-Dist: click<9,>=8.1.7
Requires-Dist: httpx<0.29,>=0.28.0
Requires-Dist: pandas<3,>=2.2.2
Requires-Dist: pyjwt[crypto]<3,>=2.9.0
Requires-Dist: pyyaml<7,>=6.0.2
